{
  "gitSyncId": "674ac487458c5653a9969d30_de3e5fdb-bb6d-407d-8a93-09e3b5eb2bb0",
  "id": "Vị Trí An Toàn_JSObject1.navigateToMap",
  "pluginId": "js-plugin",
  "pluginType": "JS",
  "unpublishedAction": {
    "actionConfiguration": {
      "encodeParamsToggle": true,
      "jsArguments": [],
      "paginationType": "NONE",
      "timeoutInMillisecond": 10000
    },
    "collectionId": "Vị Trí An Toàn_JSObject1",
    "confirmBeforeExecute": false,
    "datasource": {
      "isAutoGenerated": false,
      "name": "UNUSED_DATASOURCE",
      "pluginId": "js-plugin"
    },
    "dynamicBindingPathList": [
      {
        "key": "body"
      }
    ],
    "executeOnLoad": false,
    "fullyQualifiedName": "JSObject1.navigateToMap",
    "name": "navigateToMap",
    "pageId": "Vị Trí An Toàn",
    "userSetOnLoad": false
  }
}